mlossp/__init__.py
mlossp/converter.py
mlossp/dataloader.py
mlossp/globals.py
mlossp/preprocessor.py
mlossp/formatters/__init__.py
mlossp/formatters/formatters.py
mlossp-2.3.post1.dist-info/METADATA
mlossp-2.3.post1.dist-info/WHEEL
mlossp-2.3.post1.dist-info/licenses/LICENSE
mlossp-2.3.post1.dist-info/RECORD
