Metadata-Version: 2.3
Name: mlossp
Version: 2.3.post1
Summary: A package to spatially join and concatenate Satellite data into time series.
Author: TripIe
License:                                  Apache License
License-File: LICENSE
Classifier: License :: OSI Approved :: Apache Software License
Classifier: Operating System :: OS Independent
Classifier: Programming Language :: Python :: 3
Requires-Python: >=3.10
Requires-Dist: dask==2024.1.1
Requires-Dist: geopandas==0.14.2
Requires-Dist: geopy==2.4.1
Requires-Dist: h5netcdf==1.3.0
Requires-Dist: netcdf4==1.6.5
Requires-Dist: netcdf==66.0.2
Requires-Dist: numpy==1.26.2
Requires-Dist: pandas==2.2.0
Requires-Dist: pyarrow==15.0.0
Requires-Dist: pyogrio==0.7.2
Requires-Dist: rasterio==1.3.9
Requires-Dist: tqdm==4.66.1
Requires-Dist: xarray==2024.1.1
